README.md
setup.py
src/pseq.py
src/pseq.egg-info/PKG-INFO
src/pseq.egg-info/SOURCES.txt
src/pseq.egg-info/dependency_links.txt
src/pseq.egg-info/top_level.txt