Metadata-Version: 2.1
Name: pseq
Version: 2.0.2
Summary: A framework for parallel processing of sequences.
Home-page: https://github.com/luismsgomes/pseq
Author: Luís Gomes
Author-email: luismsgomes@gmail.com
License: GPLv3
Keywords: sequence parallel multiprocessing process subprocess
Platform: UNKNOWN
Classifier: Development Status :: 4 - Beta
Classifier: License :: OSI Approved :: GNU General Public License v3 (GPLv3)
Classifier: Programming Language :: Python :: 3.8
